{"death_data":[{"X":0,"Y":0}],"pop_data":[{"X":0,"Y":1000},{"X":1,"Y":981},{"X":2,"Y":960},{"X":3,"Y":937},{"X":4,"Y":933},{"X":5,"Y":921},{"X":6,"Y":916},{"X":7,"Y":902},{"X":8,"Y":904},{"X":9,"Y":900},{"X":10,"Y":885},{"X":11,"Y":869},{"X":12,"Y":851},{"X":13,"Y":827},{"X":14,"Y":815},{"X":15,"Y":804},{"X":16,"Y":797},{"X":17,"Y":778},{"X":18,"Y":779},{"X":19,"Y":763},{"X":20,"Y":743},{"X":21,"Y":733},{"X":22,"Y":731},{"X":23,"Y":720},{"X":24,"Y":707},{"X":25,"Y":703},{"X":26,"Y":692},{"X":27,"Y":684},{"X":28,"Y":674},{"X":29,"Y":663},{"X":30,"Y":649},{"X":31,"Y":639},{"X":32,"Y":635},{"X":33,"Y":634},{"X":34,"Y":617},{"X":35,"Y":614},{"X":36,"Y":611},{"X":37,"Y":605},{"X":38,"Y":602},{"X":39,"Y":587},{"X":40,"Y":588},{"X":41,"Y":577},{"X":42,"Y":564},{"X":43,"Y":551}],"tree_data":{"Name":"root","Color":"","children":[{"Name":"Oenoos lytraithia","Color":"#15b794"},{"Name":"Styloplasta thrixlyta","Color":"#eff123"},{"Name":"Cryptourra thonisparia","Color":"#ce4697"},{"Name":"Histiorea lepisetra","Color":"#5b50ad"},{"Name":"Pseudozoma auraesta","Color":"#8261b5"},{"Name":"Viboemera trimabaxa","Color":"#1f3076"},{"Name":"Pneumomantha diraeta","Color":"#88bb3e"},{"Name":"Stilboifex fagusetta","Color":"#068d43"},{"Name":"Tectoius theralyra","Color":"#4b9933"},{"Name":"Heliomus trophospiola","Color":"#75bfe8"},{"Name":"Toxoetto dontariona","Color":"#d10ec6"},{"Name":"Sporoula stylisara","Color":"#a5d104"},{"Name":"Borenoeni amphosella","Color":"#4b24c1"},{"Name":"Cyanonica trophosesta","Color":"#a356bc"},{"Name":"Phyllocrani crinustyra","Color":"#fe344a"},{"Name":"Phycoolax bactrapnea","Color":"#5f272b"},{"Name":"Fibroalis phytontana","Color":"#c84165"},{"Name":"Mycoon ganaella","Color":"#b2df4c"},{"Name":"Botanorea coronalica","Color":"#31a5ed"},{"Name":"Sphenocion thymaretta","Color":"#391e34"},{"Name":"Amiokora araxxira","Color":"#1b5f38"},{"Name":"Idioixus opiusrata","Color":"#b0ec29"},{"Name":"Histiogona filamelia","Color":"#b6f69a"},{"Name":"Cephaloolax xylatima","Color":"#8e8397"},{"Name":"Mesovena ntheadota","Color":"#9d504d"},{"Name":"Phyllonea zonaetta","Color":"#fa05b4"},{"Name":"Genoifex theravena","Color":"#bb6063"},{"Name":"Meristophora trophosplina","Color":"#518219"},{"Name":"Conchomus thecaolia","Color":"#ac98a9"},{"Name":"Logicoius phylissema","Color":"#414cfc"},{"Name":"Protozona scelisxesa","Color":"#696ecd"},{"Name":"Holoalix rhodosmixa","Color":"#9e9dde"},{"Name":"Genorhea dyxabina","Color":"#8dca65"},{"Name":"Allogaster stomabaxa","Color":"#32a9ee"},{"Name":"Stylopalo thamusdyla","Color":"#0f19e7"},{"Name":"Rhizoa lithosvela","Color":"#7c0a95"},{"Name":"Styloina phyllustosa","Color":"#dbcb8e"},{"Name":"Pelagogona culafilla","Color":"#780692"},{"Name":"Thermocopia thecamana","Color":"#0bd3c0"},{"Name":"Heliocrani phagusylus","Color":"#7855bb"},{"Name":"Metoodona ornisina","Color":"#8c91fa"},{"Name":"Lysonecto thermaix","Color":"#7bc187"},{"Name":"Vadoix ntheaxeus","Color":"#dadc46"},{"Name":"Ultoochora dyxalica","Color":"#b58235"},{"Name":"Pelagoinella meliathea","Color":"#df1490"},{"Name":"Rheobata tinavosa","Color":"#155237"},{"Name":"Monopyra arzalyra","Color":"#0bdff7"},{"Name":"Podoluta coccustura","Color":"#a9b22f"},{"Name":"Acidirea pathaella","Color":"#221258"},{"Name":"Cyanomera cetusmyxa","Color":"#4354aa"},{"Name":"Ethoella teraesta","Color":"#d68f1e"},{"Name":"Phyllocyma pteraxana","Color":"#548377"},{"Name":"Helioella xylama","Color":"#df6bdc"},{"Name":"Dinofira thecacora","Color":"#bb4e83"},{"Name":"Isoochora clytiavaria","Color":"#7e2e86"},{"Name":"Macrorina natesolia","Color":"#cd31a9"},{"Name":"Geolipa somaetra","Color":"#e5947b"},{"Name":"Allomus stomaess","Color":"#8386da"},{"Name":"Micromura lexazella","Color":"#c8af55"},{"Name":"Hemiico cotismexia","Color":"#9b707e"},{"Name":"Cyanotius tanosora","Color":"#b02038"},{"Name":"Dinoeus corisgonia","Color":"#c3a9a5"},{"Name":"Cirrhonica typhasaxa","Color":"#b0129a"},{"Name":"Ampheloodona carpaxus","Color":"#e3642f"},{"Name":"Acanthopatha pterasaxa","Color":"#706368"},{"Name":"Psiloplasta viciaina","Color":"#36cb92"},{"Name":"Pneumocion zymasata","Color":"#2e7d87"},{"Name":"Thermovora phoniatana","Color":"#3f8ac2"},{"Name":"Thyronauta cycluscora","Color":"#c91362"},{"Name":"Bacilloa xylonretta","Color":"#540289"},{"Name":"Thermostoma spilaylus","Color":"#0d114f"},{"Name":"Orthoeta dyxavena","Color":"#fe45e0"},{"Name":"Holoinus dromaxana","Color":"#8677fc"},{"Name":"Nectorina pectrafilla","Color":"#13d319"},{"Name":"Logicomyra scelisata","Color":"#657311"},{"Name":"Pseudopara coccuslica","Color":"#6f7b69"},{"Name":"Bacillovena phaguszexa","Color":"#602871"},{"Name":"Intrainis feraxeta","Color":"#1f7be6"},{"Name":"Canthovaro voruspylus","Color":"#bb849f"},{"Name":"Clavinauta amphosvela","Color":"#1cf735"},{"Name":"Glycorix nemesveria","Color":"#69acf2"},{"Name":"Xyloyx cotisgusa","Color":"#644c60"},{"Name":"Vadoluta bruayra","Color":"#ad2677"},{"Name":"Antialix phoniaora","Color":"#a24591"},{"Name":"Vascocis nemapiola","Color":"#8dbf57"},{"Name":"Charactoinella amphosella","Color":"#ab97f4"},{"Name":"Alaioeta thrixsata","Color":"#020905"},{"Name":"Bacilloaspis nothaloma","Color":"#b3468d"},{"Name":"Glycovena zonayra","Color":"#9edbba"},{"Name":"Nectomus ferayla","Color":"#9ab708"},{"Name":"Conchostoma spirisala","Color":"#15f153"},{"Name":"Phycoxira cycluszona","Color":"#e6c9d7"},{"Name":"Cyanorhynchus phyllusthea","Color":"#ef789f"},{"Name":"Hepatolipa sphexxeta","Color":"#7b8e0f"},{"Name":"Neurozona xenialica","Color":"#4d2a45"},{"Name":"Hydratolora phagusyra","Color":"#8af02b"},{"Name":"Algiolura silamixa","Color":"#b6cbca"},{"Name":"Barylipa thecaothia","Color":"#6d6644"},{"Name":"Orthohama thonispnea","Color":"#27ec93"},{"Name":"Polyeus sphenix","Color":"#810ea5"},{"Name":"Alloianus araxlica","Color":"#47e917"},{"Name":"Ventolitho thamaolia","Color":"#b64dd6"},{"Name":"Tychopyra amphosdola","Color":"#4112c6"},{"Name":"Stilboarix nateslexa","Color":"#a0410c"},{"Name":"Phycoxalis aurama","Color":"#772f1c"},{"Name":"Mentoplasta corislica","Color":"#3eec6b"},{"Name":"Glycopara xylonzexa","Color":"#26f444"},{"Name":"Viboetto diraina","Color":"#2e9c04"},{"Name":"Anthrocapa echnanara","Color":"#097af0"},{"Name":"Paranocroceus sphexsaxa","Color":"#08c968"},{"Name":"Dendrogaster pleurarota","Color":"#8cbe6a"},{"Name":"Lithophyta opiusixa","Color":"#0ac3b4"},{"Name":"Podoxalis thecaida","Color":"#f7c698"},{"Name":"Dermoon trimapiola","Color":"#133cf3"},{"Name":"Mentovena nidagma","Color":"#293b92"},{"Name":"Arcoata sporaeus","Color":"#535b94"},{"Name":"Flavolora sapismelia","Color":"#7ccc86"},{"Name":"Monoesta thalmaxeus","Color":"#296541"},{"Name":"Megatius domistura","Color":"#a0a7cb"},{"Name":"Anthrolipa cepsveria","Color":"#24f872"},{"Name":"Pyropina ntheacora","Color":"#1a9f59"},{"Name":"Nasonema cephalusxesa","Color":"#d076e1"},{"Name":"Stilbospira chirruszuma","Color":"#c6cdc9"},{"Name":"Phagootta lexaeus","Color":"#c90bf4"},{"Name":"Velocierus caudatima","Color":"#f3fdda"},{"Name":"Barystoma pedisdira","Color":"#b910ba"},{"Name":"Rotomantha planaess","Color":"#ce0b09"},{"Name":"Pyloroio phagustus","Color":"#661cda"},{"Name":"Lysodema flospnea","Color":"#9eb062"},{"Name":"Cladous cotiseta","Color":"#78ce08"},{"Name":"Herpocapa claduszela","Color":"#3910e1"},{"Name":"Megaoxia bruaae","Color":"#a2c64d"},{"Name":"Sporoferus pleuraula","Color":"#d39414"},{"Name":"Metoix planagusa","Color":"#ed9aeb"},{"Name":"Claviico phaguslica","Color":"#7f6e6a"},{"Name":"Neopora sphentus","Color":"#e41b87"},{"Name":"Pyritorina thamusora","Color":"#f59cff"},{"Name":"Aeroda fagusyna","Color":"#fd8783"},{"Name":"Nephroum philaiella","Color":"#65e60c"},{"Name":"Melanotora culaeta","Color":"#07aea7"},{"Name":"Mycoata sarisina","Color":"#556b44"},{"Name":"Anoxira zonavaria","Color":"#edd521"},{"Name":"Protovena cladusulus","Color":"#6b30cd"},{"Name":"Tychoinis eraetta","Color":"#93a85c"},{"Name":"Trichopara spondylalima","Color":"#d76a5e"},{"Name":"Polygaster tylaae","Color":"#3fdda9"},{"Name":"Electrobata carcarata","Color":"#8d5071"},{"Name":"Arcolita thyraara","Color":"#8bbf81"},{"Name":"Spinodera tonosyx","Color":"#87d78c"},{"Name":"Stratoinus nothaxira","Color":"#6b1b21"},{"Name":"Phlebolora fagusella","Color":"#24929c"},{"Name":"Ankyloico cotisalta","Color":"#c886f6"},{"Name":"Ultoluta caudaxera","Color":"#dbcbe4"},{"Name":"Phylloinus thyraplia","Color":"#7d21f9"},{"Name":"Pseudolynx tatuspiola","Color":"#6a024c"},{"Name":"Kinois blastalyra","Color":"#e95449"},{"Name":"Phycolora cyclusmana","Color":"#cafac4"},{"Name":"Dinofira odontosa","Color":"#7bbc98"},{"Name":"Zoopatha cephalusmana","Color":"#30f241"},{"Name":"Psilous therasema","Color":"#2412e0"},{"Name":"Morphorhynchus phaora","Color":"#d940aa"},{"Name":"Velociix stomayx","Color":"#ebac85"},{"Name":"Trichovora vescathea","Color":"#af47a8"},{"Name":"Isocoris phaxina","Color":"#f1a899"},{"Name":"Lactoius thamadoma","Color":"#73586e"},{"Name":"Scleroari ornissema","Color":"#0693e7"},{"Name":"Lithoyx tonosxeta","Color":"#860b29"},{"Name":"Isoella eidosplia","Color":"#cf67eb"},{"Name":"Pyritotoma odongusa","Color":"#96f39d"},{"Name":"Zonacis feragila","Color":"#84a8d2"},{"Name":"Genodera pectravena","Color":"#0275f4"},{"Name":"Metoochora lithanara","Color":"#da6d00"},{"Name":"Tectovora opiustura","Color":"#11d0c0"},{"Name":"Aerootta amphoszona","Color":"#1c0df6"},{"Name":"Orthoidus genadota","Color":"#d0fb5f"},{"Name":"Psiloixus philaylus","Color":"#641dd5"},{"Name":"Polyos carpatus","Color":"#88dee2"},{"Name":"Axium pathaxera","Color":"#183caa"},{"Name":"Phagotius phagusisa","Color":"#f5dafe"},{"Name":"Brachyrhea gananata","Color":"#9da32d"},{"Name":"Poetoalis prinaoidea","Color":"#f897cc"},{"Name":"Cirrhospira algasena","Color":"#46e13b"},{"Name":"Mikroyma cinctalena","Color":"#8b8b3b"},{"Name":"Pyritoodona phoniagama","Color":"#a670a9"},{"Name":"Zonainis xylatosa","Color":"#c2ca29"},{"Name":"Vadoari philaesta","Color":"#c3c11f"},{"Name":"Ventrovena semalima","Color":"#345af2"},{"Name":"Geophytoius dontayna","Color":"#64eaf9"},{"Name":"Microvaro stomama","Color":"#04e6f5"},{"Name":"Ankylopalo phyllusdyla","Color":"#bc1ea3"},{"Name":"Ventroium cyclusmixa","Color":"#e111cf"},{"Name":"Stratomus viciaodes","Color":"#14b339"},{"Name":"Gastromina colusodes","Color":"#9f7b16"},{"Name":"Chondropara retisnara","Color":"#95cf9c"},{"Name":"Osteoifex feramora","Color":"#62ed68"},{"Name":"Pelagoferus thalmapora","Color":"#0e692d"},{"Name":"Necrovena culpaata","Color":"#1d2631"},{"Name":"Rotoxalis colorariona","Color":"#ed5175"},{"Name":"Phrenoma menavela","Color":"#a29bc5"},{"Name":"Protoylis nectesyx","Color":"#91d758"},{"Name":"Canthoania auraina","Color":"#7de8c7"},{"Name":"Kinoferax thonisplina","Color":"#b67b58"},{"Name":"Algioina hallaxula","Color":"#d0a55c"},{"Name":"Zygoata corisana","Color":"#48d9b6"},{"Name":"Conchoeus bruayna","Color":"#52e2a1"},{"Name":"Rhizoochora tribacora","Color":"#d92d67"},{"Name":"Meristoluta bactrazexa","Color":"#36c459"},{"Name":"Hypoinis dyxalima","Color":"#a99b54"},{"Name":"Acidiceps cladusa","Color":"#d8f85f"},{"Name":"Zonaeni meliaetta","Color":"#5199d4"},{"Name":"Panthocroceus araxtima","Color":"#714986"},{"Name":"Nasoxira araxella","Color":"#ae2778"},{"Name":"Herbostoma xuramixa","Color":"#919a3c"},{"Name":"Hypofira cladussena","Color":"#8b5aa5"},{"Name":"Holoon tanosnema","Color":"#b42335"},{"Name":"Pelagobata eidosithia","Color":"#829bf7"},{"Name":"Ventopara bruabina","Color":"#07576b"},{"Name":"Electroluta clytiaeria","Color":"#a65a76"},{"Name":"Lipoxera cephalusis","Color":"#70d2ef"},{"Name":"Homooxia ornisalta","Color":"#0a2bef"},{"Name":"Amphelonyra thecavella","Color":"#417e7f"},{"Name":"Pseudoeus auratyra","Color":"#5ddb44"},{"Name":"Arcoyx sporaeria","Color":"#57441f"},{"Name":"Calycostoma arzaum","Color":"#80f804"},{"Name":"Polybeta clytiaella","Color":"#82c40c"},{"Name":"Tychocis lapsodota","Color":"#1f19c7"},{"Name":"Ventrogaster cinctusa","Color":"#78571f"},{"Name":"Allozona crinusoza","Color":"#91be0e"},{"Name":"Nectonauta ceracoma","Color":"#7deaad"},{"Name":"Protoxalis viciara","Color":"#73c079"},{"Name":"Oenofero rhizavina","Color":"#9fd3dd"},{"Name":"Mentovora xuraana","Color":"#ee1fb5"},{"Name":"Tectocis pectraxira","Color":"#4c9255"},{"Name":"Hierolitho bactrazona","Color":"#bbd5de"},{"Name":"Monophorus leptayna","Color":"#654d93"},{"Name":"Tectocion carpasema","Color":"#26df6d"},{"Name":"Tychophorus lexaana","Color":"#74d1f4"},{"Name":"Fructolipa algatera","Color":"#ec679a"},{"Name":"Diplotema thrixetra","Color":"#760520"},{"Name":"Foliofira domisgama","Color":"#fd37c7"},{"Name":"Thermonex tylusxuma","Color":"#204fc7"},{"Name":"Lactomina lithoson","Color":"#5ce0a7"},{"Name":"Trichofero thamuszala","Color":"#431e95"},{"Name":"Pentavaro lepisella","Color":"#a63236"},{"Name":"Tectolitho morphaium","Color":"#c0e7d8"},{"Name":"Hypomura dyxamixa","Color":"#c6dc08"},{"Name":"Herbohama bryaeria","Color":"#f412b1"},{"Name":"Borenous semayx","Color":"#ff2ede"},{"Name":"Hemiesta hallavena","Color":"#2d4373"},{"Name":"Chondropara phagusdola","Color":"#6334af"},{"Name":"Lipostoma pediseria","Color":"#a0f711"},{"Name":"Volocion nothazella","Color":"#7c21fe"},{"Name":"Cyanotoma cephalusdira","Color":"#3b8298"},{"Name":"Arcoio sphendola","Color":"#677382"},{"Name":"Lactoilis chirrusyna","Color":"#1359d4"},{"Name":"Blastolitho corisveria","Color":"#77812e"},{"Name":"Heliocis glossaon","Color":"#7d00c3"},{"Name":"Pneumodema dyxaara","Color":"#0347a6"},{"Name":"Lipovora domisrata","Color":"#d732e5"},{"Name":"Calycotoma crotayra","Color":"#036170"},{"Name":"Mikroilis ganalexa","Color":"#14a223"},{"Name":"Saprocis filaynta","Color":"#6ce55d"},{"Name":"Genois trophosa","Color":"#936413"},{"Name":"Velociius algadira","Color":"#85019d"},{"Name":"Axipara teramixa","Color":"#3d2207"},{"Name":"Spinoilis pathacola","Color":"#e5ab5d"},{"Name":"Rhizonica glycusdota","Color":"#ea003c"},{"Name":"Osteoaris spilalena","Color":"#5db9db"},{"Name":"Geophytopalo silaothia","Color":"#01a2f2"},{"Name":"Lithorhynchus pteratella","Color":"#036973"},{"Name":"Hepatocela xylapora","Color":"#7c8c09"},{"Name":"Phylloxita tatusnara","Color":"#519a5e"},{"Name":"Tychonema dontaxana","Color":"#bedf16"},{"Name":"Rotoella dyxazella","Color":"#460707"},{"Name":"Toxofira pleuraoidea","Color":"#352939"},{"Name":"Sporolipa cinctalyra","Color":"#899c7e"},{"Name":"Pelagonauta cotisesta","Color":"#1546f1"},{"Name":"Panthoico sapisgama","Color":"#326996"},{"Name":"Podoinus tylusa","Color":"#925c34"},{"Name":"Algioorix lithalyta","Color":"#538b8b"},{"Name":"Hepatolemma eraxus","Color":"#eb5ddf"},{"Name":"Mycoippa bryayx","Color":"#7b3d40"},{"Name":"Epizoma pnoeatana","Color":"#03e7a8"},{"Name":"Mesogaster thermanata","Color":"#cc6d68"},{"Name":"Ethotoma nectesmana","Color":"#d726a7"},{"Name":"Pseudovena synthaoidea","Color":"#9d8c91"},{"Name":"Vadoeni opsidarota","Color":"#aeb9ab"},{"Name":"Metrotix feraeus","Color":"#8e3f4f"},{"Name":"Hydroeta crinuspiola","Color":"#059f59"},{"Name":"Spinonauta feraana","Color":"#a6e6c7"},{"Name":"Phrenovena phoniaceris","Color":"#1a9997"},{"Name":"Blastoium gasterlica","Color":"#1182ef"},{"Name":"Mentoodona pathafilla","Color":"#1b5456"},{"Name":"Voloum xylonmora","Color":"#ba4f93"},{"Name":"Homonica hallaxeta","Color":"#d6701f"},{"Name":"Acanthomina curaiana","Color":"#4e165b"},{"Name":"Pachyifex clytiasema","Color":"#85dbc1"},{"Name":"Cephaloylis chirrusbaxa","Color":"#90daba"},{"Name":"Philoxira dyxadyla","Color":"#038041"},{"Name":"Herboalix typhanata","Color":"#d8b01b"},{"Name":"Granulodera sphenzexa","Color":"#e7a840"},{"Name":"Rotoium opsidatera","Color":"#9d9e23"},{"Name":"Pseudooris theraodes","Color":"#59fd3c"},{"Name":"Teleorhea curanixa","Color":"#3fab62"},{"Name":"Hemilora goniaynta","Color":"#3e5c5c"},{"Name":"Endoiana bryaxeta","Color":"#c58ecd"},{"Name":"Acanthospira hallatrela","Color":"#9fa701"},{"Name":"Neoinella cetuscola","Color":"#4d34bc"},{"Name":"Pentazona moniaeta","Color":"#c6042e"},{"Name":"Teleoyma ganadota","Color":"#451a67"},{"Name":"Lipoania philacora","Color":"#37673f"},{"Name":"Mentonema pathavina","Color":"#1b373f"},{"Name":"Xylozona moniaitas","Color":"#fee303"},{"Name":"Phyllotema erayra","Color":"#98563f"},{"Name":"Tectopalo thalmaora","Color":"#3adff0"},{"Name":"Neurocopia dyxanata","Color":"#8be795"},{"Name":"Anthroxita somania","Color":"#483d09"},{"Name":"Ethoxalis oplolexa","Color":"#c1dcaf"},{"Name":"Phrenolynx chytraoidea","Color":"#9d78a1"},{"Name":"Hydratovora drilusesta","Color":"#8eeaa5"},{"Name":"Ventroania xuraithia","Color":"#19ecda"},{"Name":"Hierolemma ceraulus","Color":"#13ebcc"},{"Name":"Zymospira prinaesta","Color":"#43f8cb"},{"Name":"Monohama xuravosa","Color":"#d4b4fd"},{"Name":"Rotootta tropusulus","Color":"#d7710b"},{"Name":"Nephropara thyravena","Color":"#d975d0"},{"Name":"Nephrous leptaxus","Color":"#5e53a6"},{"Name":"Thermopara colusxana","Color":"#830109"},{"Name":"Xyloix xylonolia","Color":"#2bf367"},{"Name":"Helioum thymaix","Color":"#2e1a34"},{"Name":"Plastopora cepsxus","Color":"#78587b"},{"Name":"Botanophyta thyrasaxa","Color":"#64a7fc"},{"Name":"Acidilynx ornisyna","Color":"#84e151"},{"Name":"Scalorhea tylaynta","Color":"#67028a"},{"Name":"Pachyotta coriscora","Color":"#fae455"},{"Name":"Tectonauta culpamyxa","Color":"#772507"},{"Name":"Kinoma dyxaella","Color":"#000795"},{"Name":"Macrostoma branchiagila","Color":"#edf6fd"},{"Name":"Xylopina fonadota","Color":"#2f2a8b"},{"Name":"Chondrorix pleuralima","Color":"#e92d2f"},{"Name":"Hemiodona dyxayna","Color":"#73a703"},{"Name":"Rheomyra corisolia","Color":"#0e11dd"},{"Name":"Lipogona plisretta","Color":"#c4bae4"},{"Name":"Blastopina fagusyla","Color":"#b528f0"},{"Name":"Fructoina glossasata","Color":"#337a07"},{"Name":"Granulovena diragusa","Color":"#90439b"},{"Name":"Meristolipa culpaxeus","Color":"#a7dd24"},{"Name":"Canthopora critispnea","Color":"#ef8401"},{"Name":"Lactopora thalmatoma","Color":"#2b1334"},{"Name":"Oreorina sphenoza","Color":"#292119"},{"Name":"Ethopatha theraxera","Color":"#bf5854"},{"Name":"Thermoxalis bactraylus","Color":"#f84664"},{"Name":"Tectoius corisvosa","Color":"#e0e752"},{"Name":"Rhizovora genesdoma","Color":"#2ad266"},{"Name":"Aeroxera clytiacola","Color":"#b4f1e1"},{"Name":"Mycoico natesxina","Color":"#4220db"},{"Name":"Pylorolitho fagusrata","Color":"#542273"},{"Name":"Teleoon semagma","Color":"#c734c3"},{"Name":"Morphonica sternagma","Color":"#be18fa"},{"Name":"Baryoxia amphoslima","Color":"#3be68a"},{"Name":"Tricholynx dontais","Color":"#c224be"},{"Name":"Charactonyra teraella","Color":"#2b09c3"},{"Name":"Pachylynx amphoscora","Color":"#f54008"},{"Name":"Lithogaster ceragora","Color":"#ffc708"},{"Name":"Caloinis critislyta","Color":"#64097f"},{"Name":"Ethotix flosodes","Color":"#2e8861"},{"Name":"Anthrolipa nemesra","Color":"#bb0242"},{"Name":"Logicotix synthayra","Color":"#474ebd"},{"Name":"Hypoillo xuraitas","Color":"#02a79e"},{"Name":"Zygoae trimaxus","Color":"#63efed"},{"Name":"Tychocis phylisgora","Color":"#72f3a1"},{"Name":"Plastoylis viciatura","Color":"#34d7d3"},{"Name":"Zooianus odoness","Color":"#25dd5f"},{"Name":"Xyloatus dromacora","Color":"#501fda"},{"Name":"Ankylospira filais","Color":"#cfc900"},{"Name":"Blastonauta nemayra","Color":"#0f0b89"},{"Name":"Canthopyra viciazala","Color":"#c16c48"},{"Name":"Zygostoma sapisyna","Color":"#9d7917"},{"Name":"Bryoesta silaplina","Color":"#55eece"},{"Name":"Mesostoferax fugaoidea","Color":"#030b43"},{"Name":"Podovena botraxeta","Color":"#a59e9a"},{"Name":"Intraoxia therafilla","Color":"#2fe567"},{"Name":"Rhizolora filaora","Color":"#0dd7d1"},{"Name":"Muroesta carcavina","Color":"#93d699"},{"Name":"Serpentolita gmatima","Color":"#fa8236"},{"Name":"Karpoylis zonalax","Color":"#946827"},{"Name":"Psilocion baristrela","Color":"#99e6b3"},{"Name":"Ventomura glycuseria","Color":"#ba1c30"},{"Name":"Rhizomantha nectesalta","Color":"#6a62cc"},{"Name":"Topoio granaon","Color":"#d1aa86"},{"Name":"Charactoania phylistura","Color":"#6002a8"},{"Name":"Trichovora algaulus","Color":"#8dd62d"},{"Name":"Archovena spilasata","Color":"#180959"},{"Name":"Cephalomina tylooidea","Color":"#e7bb3a"},{"Name":"Heliolitho phaix","Color":"#a4762f"},{"Name":"Thermoilis typhalyta","Color":"#d63d80"},{"Name":"Axiinella hallaxira","Color":"#c29636"},{"Name":"Pylororhynchus thyranella","Color":"#507bc8"},{"Name":"Lithoorix phoniais","Color":"#118ff8"},{"Name":"Phrenoodona filaetra","Color":"#b5db71"},{"Name":"Zygoos lepislona","Color":"#ae0d20"},{"Name":"Morphobata zonayra","Color":"#bab62c"},{"Name":"Rheopodia xylonora","Color":"#f12880"},{"Name":"Podoyma lytratrela","Color":"#3dc13b"},{"Name":"Bioillo spondylatrela","Color":"#2ba764"},{"Name":"Galactoilis eraella","Color":"#c9b86f"},{"Name":"Psiloippa genadyla","Color":"#4c6715"},{"Name":"Hypoma prinasema","Color":"#7073d9"},{"Name":"Hepatolaxis glossaeria","Color":"#62696a"},{"Name":"Bioxera tinaresa","Color":"#2f166c"},{"Name":"Oenoaris zonazona","Color":"#95d01f"},{"Name":"Dendrostoma feradota","Color":"#3e88e2"},{"Name":"Fibrophyta cetusala","Color":"#e3ca31"},{"Name":"Idioemera tatusida","Color":"#b8d6e8"},{"Name":"Karpoix granamana","Color":"#22ba2f"},{"Name":"Tectomus dermanata","Color":"#daa3a5"},{"Name":"Allootta cotisbina","Color":"#5dd928"},{"Name":"Necroorix goniaeus","Color":"#78f616"},{"Name":"Olivodona natesulus","Color":"#9a7f9e"},{"Name":"Melanoesta theratosa","Color":"#2db545"},{"Name":"Charactoata phytonum","Color":"#45b492"},{"Name":"Megavena critismixa","Color":"#30d4b6"},{"Name":"Ribooris stylisvosa","Color":"#2b157c"},{"Name":"Thermoxita pathavela","Color":"#af24e9"},{"Name":"Genolaxis ntheama","Color":"#b33f1d"},{"Name":"Vericoinus critisvena","Color":"#71be44"},{"Name":"Idiorina phagusmana","Color":"#ed1fe1"},{"Name":"Blastoippa pedisvela","Color":"#9c17e1"},{"Name":"Antirix sternacola","Color":"#1714c9"},{"Name":"Hieroella ornisnia","Color":"#a6eb0d"},{"Name":"Zonalaxis aurathea","Color":"#9e0add"},{"Name":"Karponex blastavina","Color":"#cb9b3a"},{"Name":"Megais eidosus","Color":"#6a5d08"},{"Name":"Foliolita culpaisa","Color":"#2bb260"},{"Name":"Scaloinus fonavexa","Color":"#69e9ef"},{"Name":"Protoxira tyloiana","Color":"#4dc561"},{"Name":"Cephalolaxis coloramana","Color":"#aca2b3"},{"Name":"Phylloferax cinctusess","Color":"#0761b9"},{"Name":"Electrocela botratima","Color":"#7b54ec"},{"Name":"Hemorea curatosa","Color":"#eee70b"},{"Name":"Styloillo domisgama","Color":"#c18304"},{"Name":"Pseudoinis chirruslona","Color":"#537d28"},{"Name":"Vascoata tropusmexia","Color":"#2e698c"},{"Name":"Karpocis filaoza","Color":"#d52719"},{"Name":"Amioplasta thrixvosa","Color":"#a0307d"},{"Name":"Fibroari chytrazela","Color":"#d13abb"},{"Name":"Idioium bryayx","Color":"#501e6f"},{"Name":"Morphoinella ferapora","Color":"#79bd82"},{"Name":"Olivoella thalmavela","Color":"#f595be"},{"Name":"Toponema theraixa","Color":"#525020"},{"Name":"Zygoxera botrazella","Color":"#96bae0"},{"Name":"Pentailis pyraoidea","Color":"#6edcc1"},{"Name":"Tychoyma phavena","Color":"#588379"},{"Name":"Necroari cerayx","Color":"#bf6395"},{"Name":"Piropalo cetusvexa","Color":"#9f03f8"},{"Name":"Claviius thyraantha","Color":"#318aa8"},{"Name":"Spatiourra crotaora","Color":"#47bd24"},{"Name":"Cirrhoferus opsidaplia","Color":"#b6ee60"},{"Name":"Intraaris lithossema","Color":"#454958"},{"Name":"Polyochora nectesgma","Color":"#e7417a"},{"Name":"Protozoa spondylastra","Color":"#a69a68"},{"Name":"Hologona dynessata","Color":"#54eee3"},{"Name":"Ventropyra fonazexa","Color":"#6ca479"},{"Name":"Protorix oploxula","Color":"#0abfdf"},{"Name":"Zonaari lisxuma","Color":"#bf561f"},{"Name":"Polyrix domisalta","Color":"#58bdd1"},{"Name":"Plantoeta colusora","Color":"#082777"},{"Name":"Mesostoessa goniaesta","Color":"#867106"},{"Name":"Baryochora maniaon","Color":"#45fda5"},{"Name":"Topoixus plantaoza","Color":"#1c249d"},{"Name":"Necroxalis plantaatus","Color":"#e1f557"},{"Name":"Nephronema synthathea","Color":"#52b6a3"},{"Name":"Polyzoa pyraae","Color":"#eb51ad"},{"Name":"Thyroa zonatyra","Color":"#3468e3"},{"Name":"Algioilis maniaisa","Color":"#5b8936"},{"Name":"Oenostoma maniadira","Color":"#05f3eb"},{"Name":"Melanoysis silaitas","Color":"#fa42c0"},{"Name":"Zoolynx leptais","Color":"#4b464a"},{"Name":"Monoarix bracamora","Color":"#100e79"},{"Name":"Electrodema vorusina","Color":"#3fa34f"},{"Name":"Charactotora clytiaiella","Color":"#d5761c"},{"Name":"Velociinis optatrela","Color":"#872b1f"},{"Name":"Thermois terapiola","Color":"#d46163"},{"Name":"Gastrofira ganayx","Color":"#3ab736"},{"Name":"Olivophyta cetusixa","Color":"#922e1b"},{"Name":"Mentovena coccusum","Color":"#982bcb"},{"Name":"Nectocapa hallaxesa","Color":"#d9c66e"},{"Name":"Rhizocroceus pyratella","Color":"#1fafc1"},{"Name":"Archopora coluslena","Color":"#4e9d3d"},{"Name":"Anthrourra coccusala","Color":"#f177e7"},{"Name":"Folious tylusiella","Color":"#25d1f4"},{"Name":"Oxyium chirrusgama","Color":"#dd51ff"},{"Name":"Mycoalis cotavina","Color":"#93b25d"},{"Name":"Psilophorus vaxasata","Color":"#fc3380"},{"Name":"Philozoa araxyra","Color":"#08b734"},{"Name":"Flavotema driluspylus","Color":"#ab9f4c"},{"Name":"Serpentotora algatoma","Color":"#16e6f7"},{"Name":"Anthrooxia plantaixa","Color":"#cb3a56"},{"Name":"Rheotheca vaxatoma","Color":"#dcfb1e"},{"Name":"Hemiippa corismora","Color":"#fbd4ce"},{"Name":"Meganema rhodosora","Color":"#471d80"},{"Name":"Stilbofira thonisixa","Color":"#c7de96"},{"Name":"Mikrotix thermacoma","Color":"#e66a74"},{"Name":"Vascofira chirrusxira","Color":"#aba594"},{"Name":"Fibroinis retisodes","Color":"#978df6"},{"Name":"Nasotema dirazeta","Color":"#1928d9"},{"Name":"Aeromina zonaalta","Color":"#e3b792"},{"Name":"Pachyda morphaylus","Color":"#4add9b"},{"Name":"Acanthohama algathea","Color":"#7823cf"},{"Name":"Macrozoa phreaora","Color":"#f2c9b2"},{"Name":"Xylostoma gmapylus","Color":"#b68a27"},{"Name":"Folionea xylanella","Color":"#9f3ad4"},{"Name":"Lithosomia lapsovella","Color":"#a1e1b9"},{"Name":"Caloyx bryaithia","Color":"#7af7e7"},{"Name":"Orthoinus dynesxeria","Color":"#6e39a2"},{"Name":"Mentoalis dynesodes","Color":"#3db2ec"},{"Name":"Pylorolura pectrabaxa","Color":"#cf0816"},{"Name":"Alaioatus fonaella","Color":"#c20b3f"},{"Name":"Chondroorix lisxira","Color":"#f7c4c2"},{"Name":"Granulonauta phyllusithia","Color":"#25a3d9"},{"Name":"Thermolora theratura","Color":"#da5b19"},{"Name":"Hemiyma tribalica","Color":"#8156bf"},{"Name":"Calycoalis filatera","Color":"#b5e4f9"},{"Name":"Amioinella nidafala","Color":"#ccd4ac"},{"Name":"Arcocoris zonapora","Color":"#2e71c7"},{"Name":"Mesopodia drilusina","Color":"#5c22c5"},{"Name":"Mesopyra auradyla","Color":"#43b3a2"},{"Name":"Idiomina phazuma","Color":"#241539"},{"Name":"Galactonecto rhizarota","Color":"#8ea805"},{"Name":"Pneumonyra tylovexa","Color":"#4af257"},{"Name":"Histionyra dermania","Color":"#e1eda1"},{"Name":"Histiolemma blastasaxa","Color":"#f2ed63"},{"Name":"Pironea tyloveria","Color":"#f3ef6a"},{"Name":"Morphoix ornisyra","Color":"#704456"},{"Name":"Pyrolynx branchiaxana","Color":"#3a9a9a"},{"Name":"Velociluta sarisvixa","Color":"#78a337"},{"Name":"Scalodex xylonitas","Color":"#ca65f6"},{"Name":"Homoferax lithazela","Color":"#40d737"},{"Name":"Homoeni tonosra","Color":"#6bc1a5"},{"Name":"Cirrhodona meliavaria","Color":"#be4f41"},{"Name":"Idiotheca tylusrata","Color":"#7c9900"},{"Name":"Lactoilis thonisxera","Color":"#a1ef41"},{"Name":"Tectoari coloraloma","Color":"#44c910"},{"Name":"Intratix pathamixa","Color":"#4ca8d6"},{"Name":"Xylolitho cepsitas","Color":"#8fd3d5"},{"Name":"Arcorina genaara","Color":"#753ed9"},{"Name":"Logicoinus thyrara","Color":"#0831ac"},{"Name":"Monomura tanoslica","Color":"#14c879"},{"Name":"Aerotheca spilaretta","Color":"#4f4a7b"},{"Name":"Acanthoinis opsidaplia","Color":"#d8ec05"},{"Name":"Cryptoferax tylussena","Color":"#bc5d33"},{"Name":"Spinorea chirrusxera","Color":"#f6f63b"},{"Name":"Rotoxira sphextyra","Color":"#6948e5"},{"Name":"Chlorotheca dromathea","Color":"#a39888"},{"Name":"Pododera menavosa","Color":"#3efad3"},{"Name":"Spatiomyra nothastra","Color":"#ac34dc"},{"Name":"Lysolipa culaum","Color":"#f544ce"},{"Name":"Xylomina tlexaantha","Color":"#6cafe1"},{"Name":"Spatiostoma algayna","Color":"#e0916f"},{"Name":"Cantholynx nemesxeus","Color":"#5d091e"},{"Name":"Homoolax botralica","Color":"#b7cbfe"},{"Name":"Holocroceus phyliszella","Color":"#fc4078"},{"Name":"Anooxia leptadoma","Color":"#b74ffb"},{"Name":"Granuloilis faguscora","Color":"#1cc78d"},{"Name":"Gastrotix sphexvaria","Color":"#87e3b8"},{"Name":"Nasolipa echnayna","Color":"#8c13fa"},{"Name":"Pirocrani planazexa","Color":"#e392c4"},{"Name":"Pachytema araxxira","Color":"#1e731e"},{"Name":"Olivoyma trophosala","Color":"#8cb42f"},{"Name":"Acanthofira phylisiella","Color":"#9b5542"},{"Name":"Pyritopina rhizalyra","Color":"#7b17a9"},{"Name":"Lysocopia necteszella","Color":"#534e7a"},{"Name":"Bacilloio tinayla","Color":"#341ab3"},{"Name":"Blastotoma bryaiella","Color":"#3d6698"},{"Name":"Hydratoesta petratoma","Color":"#e11e1a"},{"Name":"Tectoixus gallaata","Color":"#1ed9a9"},{"Name":"Nectoma moniapylus","Color":"#ca8736"},{"Name":"Thermooris blastaon","Color":"#90f120"},{"Name":"Intraphora nemescora","Color":"#4c7ca7"},{"Name":"Alloos chirrusxus","Color":"#978a68"},{"Name":"Paranopina lectapiola","Color":"#a21041"},{"Name":"Neuroxira odoneta","Color":"#15215f"},{"Name":"Mesootta xuraxus","Color":"#088122"},{"Name":"Saproonoma teratyra","Color":"#ca6c36"},{"Name":"Stylocopia amphosvixa","Color":"#cdacb6"},{"Name":"Scaloidus drilusalta","Color":"#516b99"},{"Name":"Epizorea phytonrata","Color":"#e9d6e0"},{"Name":"Vascoferax petraplina","Color":"#e07c06"},{"Name":"Pseudovena rhizadyla","Color":"#a300ce"},{"Name":"Nasolynx lithamixa","Color":"#1bd21e"},{"Name":"Fructous filavella","Color":"#745c7a"},{"Name":"Calocoris pinnaxuma","Color":"#bb6f1f"},{"Name":"Oreopodia tatusgma","Color":"#212276"},{"Name":"Thermopodia cinctalona","Color":"#ce3534"},{"Name":"Hemomantha opiusnema","Color":"#13e02a"},{"Name":"Spatioilis nemesess","Color":"#82fcc2"},{"Name":"Amphelopalo opiusveria","Color":"#aeb7e0"},{"Name":"Fibrodona culaxus","Color":"#2d32c6"},{"Name":"Alaiolipa ceraina","Color":"#a52c1d"},{"Name":"Lithoeni doxialexa","Color":"#4f565a"},{"Name":"Mentoinis thrixmyxa","Color":"#7227df"},{"Name":"Botanoianus plisylus","Color":"#2e4aa1"},{"Name":"Hydroessa feraxus","Color":"#cbc046"},{"Name":"Nectozoa pyrazella","Color":"#fd5770"},{"Name":"Herbopatha zonaus","Color":"#de07bf"},{"Name":"Hypophora glycusriona","Color":"#d247ff"},{"Name":"Zoootta ntheazeta","Color":"#11991d"},{"Name":"Logicolipa clytiaala","Color":"#824440"},{"Name":"Logicoianus spilatyra","Color":"#9fb7d3"},{"Name":"Spinoalis scelisora","Color":"#e2ee45"},{"Name":"Monoixus dromavaria","Color":"#3098bf"},{"Name":"Algiocroceus maniatana","Color":"#6d0cad"},{"Name":"Heliooxia vescaora","Color":"#2c8d7a"},{"Name":"Fibroari arzapylus","Color":"#d8b2b8"},{"Name":"Polylynx sternaala","Color":"#614f98"},{"Name":"Hepatobeta odonida","Color":"#81c8ef"},{"Name":"Oxytius coccusiana","Color":"#818f67"},{"Name":"Geolipa natesnixa","Color":"#75982e"},{"Name":"Melanomura thecaium","Color":"#753f1b"},{"Name":"Phycozona hallalax","Color":"#13e14d"},{"Name":"Herpootta natesvexa","Color":"#5a1c5f"},{"Name":"Hierovora opiusxesa","Color":"#568a8e"},{"Name":"Dinourra xylavaria","Color":"#f81d1b"},{"Name":"Anthrolura pinnalax","Color":"#f7e585"},{"Name":"Tectobata tylotosa","Color":"#45ed2e"},{"Name":"Glycoinis sphexynta","Color":"#783bf7"},{"Name":"Ventoplasta lithaisa","Color":"#a699e7"},{"Name":"Hydrolura araxdira","Color":"#07aedb"},{"Name":"Neuroolax tylaoidea","Color":"#351428"},{"Name":"Spatioma echnatus","Color":"#406d8d"},{"Name":"Scalopina chytracoma","Color":"#b12d41"},{"Name":"Piroonoma echnaetta","Color":"#35a628"},{"Name":"Epizoina theraium","Color":"#1fab87"},{"Name":"Lithocoris crotaus","Color":"#1284df"},{"Name":"Metrocapa vaxaetta","Color":"#0629ee"},{"Name":"Phleboluta filaae","Color":"#030893"},{"Name":"Nephrocapa sporaiana","Color":"#06c864"},{"Name":"Karpophyta corisxus","Color":"#83a092"},{"Name":"Fructolora culagora","Color":"#8edf4d"},{"Name":"Bryocopia silalena","Color":"#8066ea"},{"Name":"Phyllolipa coloraina","Color":"#f13e1f"},{"Name":"Spinootta flosparia","Color":"#781008"},{"Name":"Logicoxera cotaixa","Color":"#24b96e"},{"Name":"Osteoium filaala","Color":"#ba772b"},{"Name":"Neozoa thymalica","Color":"#5fa653"},{"Name":"Tectovena somadota","Color":"#428b49"},{"Name":"Ultofira lithaceris","Color":"#ecf8bb"},{"Name":"Helioatus maniayra","Color":"#87035f"},{"Name":"Epizoochora phreaae","Color":"#130ba4"},{"Name":"Tectopyra hallagama","Color":"#f36bf3"},{"Name":"Fibroolax culpaceris","Color":"#f334aa"},{"Name":"Phagophorus granarata","Color":"#2d51e9"},{"Name":"Pyritotix nothalexa","Color":"#e4e892"},{"Name":"Oenopatha pinnayla","Color":"#000e14"},{"Name":"Hydropora dromara","Color":"#83cc8d"},{"Name":"Lipocrani carcazela","Color":"#28342e"},{"Name":"Hemocrani semaess","Color":"#34b8d9"},{"Name":"Hydropora thecacora","Color":"#4484ea"},{"Name":"Viboius critisesta","Color":"#485613"},{"Name":"Nectoum crinusula","Color":"#bd601d"},{"Name":"Mesostoyx thalmaata","Color":"#49a3cd"},{"Name":"Anthroula rhizayla","Color":"#e39c8f"},{"Name":"Idiomura sporagama","Color":"#287b5e"},{"Name":"Foliodona doxialoma","Color":"#973a34"},{"Name":"Anthrofira xuraara","Color":"#729463"},{"Name":"Acanthopina gmaella","Color":"#51ff50"},{"Name":"Aeronea cinctania","Color":"#24ce2e"},{"Name":"Lipoula phatoma","Color":"#195d87"},{"Name":"Teleonica natessena","Color":"#0bc205"},{"Name":"Oreoico cotadira","Color":"#695906"},{"Name":"Mikrorix cinctagusa","Color":"#6bae31"},{"Name":"Geocion nemesxuma","Color":"#1c8f07"},{"Name":"Paleorhynchus fonarota","Color":"#a42ca9"},{"Name":"Saproesta moniaveria","Color":"#08cf02"},{"Name":"Lipohama oploina","Color":"#3541b0"},{"Name":"Pseudoina opiusess","Color":"#3087e8"},{"Name":"Pentacopia vescabina","Color":"#0a229d"},{"Name":"Antialix fagusyla","Color":"#58ca6e"},{"Name":"Neoessa lithatora","Color":"#ad7e43"},{"Name":"Xyloeni maniaeus","Color":"#b51059"},{"Name":"Plantooris granaolia","Color":"#60aadf"},{"Name":"Monoaspis phylispora","Color":"#254c17"},{"Name":"Oenoalis gasterisa","Color":"#b01f26"},{"Name":"Cladocrani lapsodira","Color":"#43a04b"},{"Name":"Isoarix thalmaiella","Color":"#ed6563"},{"Name":"Phrenopalo filayra","Color":"#930981"},{"Name":"Cyanonea goniatana","Color":"#7f617a"},{"Name":"Dendrozona lapsotosa","Color":"#72a9dc"},{"Name":"Cyanoos granaeta","Color":"#0af0f9"},{"Name":"Amiopatha opsidaodes","Color":"#e418d0"},{"Name":"Plantoilis xeniaoidea","Color":"#356ec3"},{"Name":"Xylopyra lexanata","Color":"#295c5c"},{"Name":"Kinoerus filaisa","Color":"#4fdc4e"},{"Name":"Dermovora bracaxula","Color":"#8e2cb7"},{"Name":"Spinoum araxxina","Color":"#27de9b"},{"Name":"Anospira vorusmana","Color":"#22183b"},{"Name":"Archomus lisida","Color":"#123599"},{"Name":"Metrorea lexabaxa","Color":"#6b8a5a"},{"Name":"Olivoilis sphenma","Color":"#da3a6b"},{"Name":"Zoocapa zymaatus","Color":"#2721ed"},{"Name":"Scaloina pinnaora","Color":"#f9fd06"},{"Name":"Piropalo nectesgila","Color":"#15bebc"},{"Name":"Hemiius spilaithia","Color":"#f60173"},{"Name":"Serpentomina genaina","Color":"#d44f53"},{"Name":"Hieroidus silaantha","Color":"#19271d"},{"Name":"Blastospira tanosgora","Color":"#d5ac34"},{"Name":"Ribonica erabina","Color":"#baf870"},{"Name":"Stilbocapa bruagama","Color":"#29cea7"},{"Name":"Herpopatha planara","Color":"#0ef54e"},{"Name":"Olivoferax fonaothia","Color":"#e22c86"},{"Name":"Anthrovaro plantadola","Color":"#d2327b"},{"Name":"Mentocela doxiaella","Color":"#368920"},{"Name":"Aerolitho ganazona","Color":"#77ce1c"},{"Name":"Protoula faguslica","Color":"#79c461"},{"Name":"Hemilora silaetra","Color":"#c07216"},{"Name":"Geophytorhea chytrazuma","Color":"#4e5af4"},{"Name":"Erythroillo cotislona","Color":"#14ee09"},{"Name":"Anoos sapispnea","Color":"#0d258e"},{"Name":"Vascoesta lytrapiola","Color":"#c63815"},{"Name":"Scleroinus thermaxira","Color":"#c6a9f8"},{"Name":"Anthrooxia spirisvena","Color":"#418d45"},{"Name":"Geoius lithaella","Color":"#cc0f12"},{"Name":"Geoluta pectraxesa","Color":"#9dd520"},{"Name":"Metoico lithaora","Color":"#535d0d"},{"Name":"Toxoidus sporaplia","Color":"#9c93d9"},{"Name":"Stilbootta stylisdira","Color":"#99ebde"},{"Name":"Anthrocoris genespora","Color":"#51ba33"},{"Name":"Protoula pedistrela","Color":"#537e2e"},{"Name":"Dinolynx sporaparia","Color":"#98939b"},{"Name":"Nasoxera eidoslena","Color":"#a92235"},{"Name":"Mesogona spilaalta","Color":"#f81aa5"},{"Name":"Fibrozoa genacora","Color":"#21e48c"},{"Name":"Stenoula coluslona","Color":"#eb2605"},{"Name":"Pneumoceps thalmavaria","Color":"#0c7baf"},{"Name":"Lactomera vescaella","Color":"#3dc1f4"},{"Name":"Scalocoris crotaxina","Color":"#7daf71"},{"Name":"Amiocrani siladira","Color":"#9fbf54"},{"Name":"Pyritoma morphagora","Color":"#61b760"},{"Name":"Mesostozoma culapiola","Color":"#a0ae2b"},{"Name":"Calycoxita coccusodes","Color":"#dc954c"},{"Name":"Antiysis zonaxina","Color":"#11eb75"},{"Name":"Scleroilis phreamora","Color":"#7675a6"},{"Name":"Hepatolora sternalena","Color":"#b7548b"},{"Name":"Herpoesta lexaitas","Color":"#6aac40"},{"Name":"Geopina thrixesta","Color":"#fab155"},{"Name":"Litholora vorusfilla","Color":"#d0d911"},{"Name":"Rhizoluta cetusora","Color":"#a987c0"},{"Name":"Pyropora pyralona","Color":"#efcc45"},{"Name":"Phylloae blastaoidea","Color":"#9c0084"},{"Name":"Brachytoma petralax","Color":"#05ea2f"},{"Name":"Oreocroceus thonisplia","Color":"#bc9f32"},{"Name":"Cryptocis thrixxira","Color":"#081578"},{"Name":"Intralaxis somaxera","Color":"#6674c0"},{"Name":"Scalotius pectrayra","Color":"#cd3a4a"},{"Name":"Hepatotheca sphexbaxa","Color":"#2559e8"},{"Name":"Psilobeta ganacora","Color":"#e2b50f"},{"Name":"Cirrhonex plantavaria","Color":"#2c6ff3"},{"Name":"Pseudoolax perlayna","Color":"#253d03"},{"Name":"Stylodex bruais","Color":"#7c67f6"},{"Name":"Lithoae arzalexa","Color":"#703bf5"},{"Name":"Scaloium retisxina","Color":"#366a0d"},{"Name":"Neurolura nemesplina","Color":"#5ad82c"},{"Name":"Serpentooris listana","Color":"#e9c0ae"},{"Name":"Stilboalix sporasema","Color":"#817378"},{"Name":"Tectoos gasterlyra","Color":"#2b1ab3"},{"Name":"Botanoius echnayra","Color":"#37b48c"},{"Name":"Zymootta dromathea","Color":"#049353"},{"Name":"Philonyra genescola","Color":"#2165a9"},{"Name":"Protomus retisxera","Color":"#42baf4"},{"Name":"Fibrophora colorazella","Color":"#7e3e72"},{"Name":"Fructoifex eidospiola","Color":"#c7e6a2"},{"Name":"Poetolynx ganaixa","Color":"#5f4a64"},{"Name":"Protozona carcacora","Color":"#038f47"},{"Name":"Xylonica phagusdyla","Color":"#062461"},{"Name":"Zonatora tylaella","Color":"#044fa3"},{"Name":"Phylloum trimamixa","Color":"#e8a3e6"},{"Name":"Toxoylis fonamyxa","Color":"#3e0bb0"},{"Name":"Microma hallaoza","Color":"#befda8"},{"Name":"Ethocis dermadota","Color":"#8bab4e"},{"Name":"Scalolora blastaella","Color":"#9a230b"},{"Name":"Electroalis stomavaria","Color":"#bc936a"},{"Name":"Pseudoum domiszella","Color":"#fb9231"},{"Name":"Xyloon tylois","Color":"#595460"},{"Name":"Antidera genesetta","Color":"#3a3598"},{"Name":"Pentacela gmatyra","Color":"#2592c6"},{"Name":"Biostoma cinctaretta","Color":"#c436f8"},{"Name":"Hepatoetto thonisa","Color":"#0409e6"},{"Name":"Vasconica lexasaxa","Color":"#d9da3e"},{"Name":"Protoinis granaetra","Color":"#2027f7"},{"Name":"Electroysis sternaus","Color":"#dcf419"},{"Name":"Fructovena ganaxesa","Color":"#17970e"},{"Name":"Phagourra retisida","Color":"#97dec6"},{"Name":"Hieroolax vorustima","Color":"#353363"},{"Name":"Zymofira domisyla","Color":"#db44ed"},{"Name":"Phylloius nidaantha","Color":"#53b5d5"},{"Name":"Electroluta blastaxina","Color":"#5dde79"},{"Name":"Pyloroxalis caudaxus","Color":"#8c7def"},{"Name":"Plastophyta stylislyta","Color":"#b36838"},{"Name":"Alaiootta cinctusma","Color":"#35ae47"},{"Name":"Clavirea phaguszeta","Color":"#1acd26"},{"Name":"Serpentoalis phreamyxa","Color":"#a41b6a"},{"Name":"Velociylis bruapnea","Color":"#13e800"},{"Name":"Hepatodex thalmaithia","Color":"#5866a0"},{"Name":"Lactoos tatusgusa","Color":"#a2bbc8"},{"Name":"Bacilloix tlexapylus","Color":"#4668c4"},{"Name":"Charactonica gmaodes","Color":"#0a4319"},{"Name":"Scalolura plantapiola","Color":"#a65fc3"},{"Name":"Monocoris critisetra","Color":"#621e8c"},{"Name":"Borenotheca ceraella","Color":"#4aab0b"},{"Name":"Psilorhea cepspnea","Color":"#c9ca06"},{"Name":"Plastoius nothalona","Color":"#fef30e"},{"Name":"Algiopina drilusmexia","Color":"#096e74"},{"Name":"Bacillorea tropuszala","Color":"#3eaad4"},{"Name":"Morphoplasta feragama","Color":"#68a702"},{"Name":"Antinex branchiaixa","Color":"#e669de"},{"Name":"Hemiilis pathabina","Color":"#12d971"},{"Name":"Pseudoluta cinctusantha","Color":"#2f7814"},{"Name":"Thermoda lithostera","Color":"#52475a"},{"Name":"Cephaloae ntheaina","Color":"#e0cf93"},{"Name":"Panthoula zymayla","Color":"#65705a"},{"Name":"Homoidus optacora","Color":"#eb54cf"},{"Name":"Pantholuta tanoszexa","Color":"#ab951c"},{"Name":"Algioaris spondylaxina","Color":"#a4e69a"},{"Name":"Pachycrani araxae","Color":"#8a2919"},{"Name":"Rheodera cotarata","Color":"#843dea"},{"Name":"Cantholora thamusala","Color":"#3b5baf"},{"Name":"Aeroilis sarisora","Color":"#c3aa27"},{"Name":"Topoiana maniatella","Color":"#3efbbd"},{"Name":"Acidiippa dontatosa","Color":"#10cb2d"},{"Name":"Kinoina cerabina","Color":"#828394"},{"Name":"Mentoxira coronaix","Color":"#257be9"},{"Name":"Psilorix pleuraara","Color":"#ec72e2"},{"Name":"Pyritoa diraixa","Color":"#13376c"},{"Name":"Plastotema branchiarota","Color":"#248612"},{"Name":"Borenoon opsidazexa","Color":"#929e05"},{"Name":"Isotius meliaon","Color":"#510861"},{"Name":"Rheoysis ntheacora","Color":"#983c69"},{"Name":"Zymoianus gmaxina","Color":"#7ba3dd"},{"Name":"Vascoos odonpora","Color":"#b0a29f"},{"Name":"Karpopodia ornisyla","Color":"#8b5fa1"},{"Name":"Axiolax stomavixa","Color":"#c0db6a"},{"Name":"Phyllocoris chirrusxera","Color":"#433966"},{"Name":"Blastorea vescavaria","Color":"#e90d6e"},{"Name":"Hydratolora odonnata","Color":"#c3fb07"},{"Name":"Hydratoluta opiusfilla","Color":"#acc5c7"},{"Name":"Hepatooris sternaretta","Color":"#2b8692"},{"Name":"Canthoma lytraxera","Color":"#c6eb6a"},{"Name":"Polyorix dontaella","Color":"#f7980d"},{"Name":"Phrenoxita thyraixa","Color":"#c9be98"},{"Name":"Cirrhoinis thamusyx","Color":"#cd4fdf"},{"Name":"Sphenoxera sphenlexa","Color":"#5663b5"},{"Name":"Pirozoa somaolia","Color":"#bbc0e2"},{"Name":"Genorix leptatima","Color":"#7bb5ad"},{"Name":"Dinomura silaxera","Color":"#6ba327"},{"Name":"Acidiium lithaana","Color":"#c45cb2"},{"Name":"Archoina coloraoza","Color":"#982438"},{"Name":"Zonaferus thyradoma","Color":"#5497fd"},{"Name":"Pyloroetto ganagma","Color":"#ee219b"},{"Name":"Nasooxia tylalax","Color":"#a1b0f4"},{"Name":"Acidiphyta goniaina","Color":"#ef33cd"},{"Name":"Bryoilis lithaeus","Color":"#89c67a"},{"Name":"Thyrolora tyluslica","Color":"#b1a6e6"},{"Name":"Teleonecto tatusnia","Color":"#21ed64"},{"Name":"Dendrotema zymagusa","Color":"#cad0bb"},{"Name":"Morphoalix theratima","Color":"#c58c80"},{"Name":"Phycorix granatera","Color":"#d5b23c"},{"Name":"Anthropodia opiusis","Color":"#fbc51a"},{"Name":"Muromura teraitas","Color":"#3c8272"},{"Name":"Toponica spiriszexa","Color":"#11e01c"},{"Name":"Tectoarix tribaella","Color":"#c20299"},{"Name":"Anthroaris thalmaix","Color":"#f2db71"},{"Name":"Pachypatha dermaylus","Color":"#7fc393"},{"Name":"Paranoico hallazela","Color":"#835569"},{"Name":"Ventrotix gallaiella","Color":"#450117"},{"Name":"Zymoeni glossaxina","Color":"#20031d"},{"Name":"Morphoippa rhodosmixa","Color":"#920688"},{"Name":"Pseudoae pleuravella","Color":"#dbf081"},{"Name":"Pseudoinella goniais","Color":"#0864b7"},{"Name":"Phycoatus cotanema","Color":"#940706"},{"Name":"Cephalokora thrixma","Color":"#7968cb"},{"Name":"Plantopodia ceravela","Color":"#8e0fea"},{"Name":"Calycoix fagusoza","Color":"#fffb6a"},{"Name":"Pentarea arzaon","Color":"#a19994"},{"Name":"Mikrogaster gastervixa","Color":"#e071cb"},{"Name":"Plastoixus cylalica","Color":"#e5aa7e"},{"Name":"Geophytonema pinnagonia","Color":"#b9492e"},{"Name":"Thermofero pinnaala","Color":"#a45248"},{"Name":"Granuloiana curaolia","Color":"#7a40a8"},{"Name":"Podopalo scelisveria","Color":"#bbca3a"},{"Name":"Kinoidus phoniamora","Color":"#d48c16"},{"Name":"Stylourra lapsoium","Color":"#8e07b0"},{"Name":"Herpodona tanositas","Color":"#3c7446"},{"Name":"Phlebozona stylisina","Color":"#c915dd"},{"Name":"Phleboilis botraella","Color":"#6c6e98"},{"Name":"Velociurra podayra","Color":"#a9bb58"},{"Name":"Electronyra genesmyxa","Color":"#0e05d8"},{"Name":"Scaloemera tonosdyla","Color":"#0397cb"},{"Name":"Isotix feraeria","Color":"#25b9f0"},{"Name":"Cladorea natesithia","Color":"#a96900"},{"Name":"Canthoium spilasaxa","Color":"#e170c6"},{"Name":"Melanovora lectaparia","Color":"#737b20"},{"Name":"Orthopina spondylanata","Color":"#158c2b"},{"Name":"Herbocis genaella","Color":"#60cb61"},{"Name":"Stenoula corisdoma","Color":"#bab778"},{"Name":"Homoilis odonnella","Color":"#a71c94"},{"Name":"Teleocis culpaolia","Color":"#08513a"},{"Name":"Calovena cephaluscoma","Color":"#dc99c5"},{"Name":"Cladoatus caudatosa","Color":"#d82045"},{"Name":"Pantholitho cetusxira","Color":"#de6cda"},{"Name":"Voloemera silamelia","Color":"#8131e4"},{"Name":"Herpoum crinusmexia","Color":"#b6d8f4"},{"Name":"Acanthoyma cetusvosa","Color":"#f2b353"},{"Name":"Histioodona culaynta","Color":"#6ccab7"},{"Name":"Glycopina bruaxana","Color":"#8db733"},{"Name":"Alaioos prinavexa","Color":"#1e3b77"},{"Name":"Anthrovora cyclusxesa","Color":"#3acff6"},{"Name":"Heliocis thecaxeria","Color":"#f73493"},{"Name":"Lipodona cepsfala","Color":"#236ccc"},{"Name":"Oenohama tlexanella","Color":"#7a5323"},{"Name":"Acidiinis gmaium","Color":"#a64294"},{"Name":"Pyritolora optaum","Color":"#6bddad"},{"Name":"Tectoio xylarata","Color":"#9d79ab"},{"Name":"Fructolipa dromama","Color":"#e045dc"},{"Name":"Amiocela coloragama","Color":"#6658b2"},{"Name":"Hieroerus culazexa","Color":"#a7e2ee"},{"Name":"Viboma fugaxera","Color":"#30e468"},{"Name":"Lactoilis pedisxeus","Color":"#4656ca"},{"Name":"Gastronica cinctagma","Color":"#11f4f2"},{"Name":"Mikrorina sapisodes","Color":"#9bbbce"},{"Name":"Mentoceps cinctagonia","Color":"#3b312c"},{"Name":"Podoinus tatusolia","Color":"#5766fa"},{"Name":"Nasoma thermaida","Color":"#4a17df"},{"Name":"Brachyius filanata","Color":"#3feeaf"},{"Name":"Phylloilis eratus","Color":"#a56462"},{"Name":"Canthous crotalima","Color":"#0ca01d"},{"Name":"Monocopia dontacola","Color":"#45395a"},{"Name":"Clavinema silaetra","Color":"#7efa61"},{"Name":"Xyloifex phagusa","Color":"#d73980"},{"Name":"Topoaspis tlexaoza","Color":"#7a26de"},{"Name":"Erythrocapa cephalusvina","Color":"#6df809"},{"Name":"Pentada thyraxeus","Color":"#177d80"},{"Name":"Ultonex fugalyta","Color":"#d0bd8b"},{"Name":"Pyronica ceratera","Color":"#19df77"},{"Name":"Brachybata typhasema","Color":"#922213"},{"Name":"Aerorhea teraesta","Color":"#3c317a"},{"Name":"Chondroessa pinnais","Color":"#81bec2"},{"Name":"Canthovaro glossaora","Color":"#6be5b8"},{"Name":"Paranozona culayna","Color":"#9aaacf"},{"Name":"Macroae spilamyxa","Color":"#c33ab8"},{"Name":"Electrolaxis philaplina","Color":"#917b6d"},{"Name":"Trichoippa opiusstra","Color":"#20b06e"},{"Name":"Sporoxira stylisnixa","Color":"#706e2f"},{"Name":"Pentaico cephalusvosa","Color":"#79b59a"},{"Name":"Teleous xeniatera","Color":"#eedfda"},{"Name":"Baryvaro plantaara","Color":"#22872d"},{"Name":"Oxylita philavena","Color":"#12d3d7"},{"Name":"Hydrotora perlasena","Color":"#a8bd5b"},{"Name":"Pelagoplasta thermaretta","Color":"#93bc99"},{"Name":"Voloceps lithoseria","Color":"#3dedf1"},{"Name":"Antiluta pyrazona","Color":"#f08049"},{"Name":"Necroippa cephalustora","Color":"#988821"},{"Name":"Bioxalis retisxus","Color":"#beaa70"},{"Name":"Vericopina stomaithia","Color":"#f13e22"},{"Name":"Megabata typhacola","Color":"#6a43ab"},{"Name":"Cryptocis natesvella","Color":"#d782e8"},{"Name":"Megaa phapnea","Color":"#4320b6"},{"Name":"Xylodera coccusnella","Color":"#0885b9"},{"Name":"Anodema fugatura","Color":"#3666ac"},{"Name":"Pylorocapa fugadota","Color":"#ad6531"},{"Name":"Mesodema nectesdota","Color":"#18be96"},{"Name":"Allofira tylaparia","Color":"#379cdc"},{"Name":"Claviaspis culaolia","Color":"#157f3d"},{"Name":"Mesostomura tatustosa","Color":"#8dc776"},{"Name":"Pneumorea xeniadola","Color":"#9c2078"},{"Name":"Epizolora philara","Color":"#a742c9"},{"Name":"Poetoilis tatuspora","Color":"#c97098"},{"Name":"Lipopina tribastra","Color":"#900c81"},{"Name":"Plantonex lithosiella","Color":"#1cb060"},{"Name":"Ribogona xylonolia","Color":"#fb3d2e"},{"Name":"Hemodex araxgila","Color":"#eb3918"},{"Name":"Megaos lectamyxa","Color":"#db4355"},{"Name":"Barypatha tropuszexa","Color":"#46de21"},{"Name":"Thermolaxis tylaxula","Color":"#4b7d7b"},{"Name":"Rototius trimamyxa","Color":"#635b07"},{"Name":"Ventrotius phylisnema","Color":"#6942ae"},{"Name":"Stilbohama cinctaess","Color":"#06a969"},{"Name":"Thermoplasta lapsocoma","Color":"#ada955"},{"Name":"Spinocela crinustura","Color":"#3163f8"},{"Name":"Cryptoix cylaxeta","Color":"#97eabc"},{"Name":"Piropalo maniaitas","Color":"#0d5809"},{"Name":"Caloemera galladota","Color":"#f6c54c"},{"Name":"Megaoxia feratoma","Color":"#76594a"},{"Name":"Borenoda lithostus","Color":"#315785"},{"Name":"Biokora thamaina","Color":"#662eaf"},{"Name":"Plastotoma ganapnea","Color":"#5dddf2"},{"Name":"Tectooris gallamixa","Color":"#f36097"},{"Name":"Dysbioella phreaparia","Color":"#03d148"},{"Name":"Anorhea cetusdola","Color":"#22b6ee"},{"Name":"Phycophyta nemesdota","Color":"#a75111"},{"Name":"Dysbioetto typhadyla","Color":"#7b23b4"}]}}
